lightinfer/__init__.py
lightinfer/cli.py
lightinfer/server.py
lightinfer-0.1.0.dist-info/METADATA
lightinfer-0.1.0.dist-info/WHEEL
lightinfer-0.1.0.dist-info/entry_points.txt
lightinfer-0.1.0.dist-info/licenses/LICENSE
lightinfer-0.1.0.dist-info/RECORD
