Metadata-Version: 2.4
Name: lightinfer
Version: 0.1.0
Summary: A lightweight bridge to serve synchronous model inference via async FastAPI.
Project-URL: Homepage, https://github.com/hscspring/lightinfer
Project-URL: Bug Tracker, https://github.com/hscspring/lightinfer/issues
Author-email: Yam <haoshaochun@gmail.com>
License-Expression: MIT
License-File: LICENSE
Classifier: Framework :: FastAPI
Classifier: License :: OSI Approved :: MIT License
Classifier: Operating System :: OS Independent
Classifier: Programming Language :: Python :: 3
Classifier: Topic :: Scientific/Engineering :: Artificial Intelligence
Requires-Python: >=3.8
Requires-Dist: fastapi>=0.68.0
Requires-Dist: pydantic>=1.8.0
Requires-Dist: uvicorn>=0.15.0
Provides-Extra: dev
Requires-Dist: build; extra == 'dev'
Requires-Dist: httpx; extra == 'dev'
Requires-Dist: pytest; extra == 'dev'
Requires-Dist: requests; extra == 'dev'
Requires-Dist: twine; extra == 'dev'
